CHANGES.txt
Dockerfile
LICENSE.txt
MANIFEST.in
README.md
VERSION.txt
icarus.py
install.sh
install_full.sh
manual.html
metaquast.py
quast-lg.py
quast.py
setup.py
quast.egg-info/PKG-INFO
quast.egg-info/SOURCES.txt
quast.egg-info/dependency_links.txt
quast.egg-info/not-zip-safe
quast.egg-info/requires.txt
quast.egg-info/top_level.txt
quast_libs/N50.py
quast_libs/__init__.py
quast_libs/aligned_stats.py
quast_libs/basic_stats.py
quast_libs/circos.py
quast_libs/contigs_analyzer.py
quast_libs/create_meta_summary.py
quast_libs/fastaparser.py
quast_libs/genemark.py
quast_libs/genes_parser.py
quast_libs/genome_analyzer.py
quast_libs/glimmer.py
quast_libs/icarus.py
quast_libs/icarus_builder.py
quast_libs/icarus_parser.py
quast_libs/icarus_utils.py
quast_libs/log.py
quast_libs/metautils.py
quast_libs/optimal_assembly.py
quast_libs/options_parser.py
quast_libs/plotter.py
quast_libs/plotter_data.py
quast_libs/qconfig.py
quast_libs/qutils.py
quast_libs/reads_analyzer.py
quast_libs/reporting.py
quast_libs/run_barrnap.py
quast_libs/run_busco.py
quast_libs/search_references_meta.py
quast_libs/unique_kmers.py
quast_libs/version.py
quast_libs/barrnap/LICENSE
quast_libs/barrnap/LICENSE.Rfam
quast_libs/barrnap/LICENSE.SILVA
quast_libs/barrnap/Makefile
quast_libs/barrnap/README.md
quast_libs/barrnap/bin/barrnap
quast_libs/barrnap/binaries/darwin/nhmmer
quast_libs/barrnap/binaries/linux/nhmmer
quast_libs/barrnap/build/12S.mito.aln
quast_libs/barrnap/build/16S.mito.aln
quast_libs/barrnap/build/build_HMMs.sh
quast_libs/barrnap/build/fix-SILVA.pl
quast_libs/barrnap/db/arc.hmm
quast_libs/barrnap/db/bac.hmm
quast_libs/barrnap/db/euk.hmm
quast_libs/barrnap/db/mito.hmm
quast_libs/bedtools/.gitignore
quast_libs/bedtools/.travis.yml
quast_libs/bedtools/LICENSE
quast_libs/bedtools/Makefile
quast_libs/bedtools/README.md
quast_libs/bedtools/RELEASE_HISTORY
quast_libs/bedtools/scripts/makeBashScripts.py
quast_libs/bedtools/scripts/vcfsort.sh
quast_libs/bedtools/src/bedtools.cpp
quast_libs/bedtools/src/annotateBed/Makefile
quast_libs/bedtools/src/annotateBed/annotateBed.cpp
quast_libs/bedtools/src/annotateBed/annotateBed.h
