Metadata-Version: 1.1
Name: quast
Version: 5.0.1
Summary: Genome assembly evaluation tool
Home-page: http://quast.sf.net
Author: Alexey Gurevich, Vladislav Saveliev, Alla Mikheenko, and others
Author-email: quast.support@cab.spbu.ru
License: GPLv2
Download-URL: https://sourceforge.net/projects/quast/files
Keywords: bioinformatics,genome assembly,metagenome assembly,visualization
Platform: Linux
Platform: OS X
Classifier: Environment :: Console
Classifier: Environment :: Web Environment
Classifier: Intended Audience :: Science/Research
Classifier: License :: OSI Approved :: GNU General Public License v2 (GPLv2)
Classifier: Natural Language :: English
Classifier: Operating System :: MacOS :: MacOS X
Classifier: Operating System :: POSIX
Classifier: Operating System :: Unix
Classifier: Programming Language :: Python
Classifier: Programming Language :: JavaScript
Classifier: Topic :: Scientific/Engineering
Classifier: Topic :: Scientific/Engineering :: Bio-Informatics
Classifier: Topic :: Scientific/Engineering :: Visualization
